flameplot/__init__.py
flameplot/examples.py
flameplot/flameplot.py
flameplot-1.1.0.dist-info/LICENSE
flameplot-1.1.0.dist-info/METADATA
flameplot-1.1.0.dist-info/WHEEL
flameplot-1.1.0.dist-info/top_level.txt
flameplot-1.1.0.dist-info/RECORD
