Metadata-Version: 2.1
Name: flameplot
Version: 1.1.0
Summary: flameplot is a python package for the quantification of local similarity across two maps or embeddings.
Home-page: https://erdogant.github.io/flameplot
Download-URL: https://github.com/erdogant/flameplot/archive/1.1.0.tar.gz
Author: Erdogan Taskesen
Author-email: erdogant@gmail.com
Classifier: Programming Language :: Python :: 3
Classifier: License :: OSI Approved :: MIT License
Classifier: Operating System :: OS Independent
Requires-Python: >=3
License-File: LICENSE
Requires-Dist: matplotlib
Requires-Dist: numpy
Requires-Dist: tqdm
Requires-Dist: scipy
Requires-Dist: imagesc
Requires-Dist: scatterd
Requires-Dist: requests
